qlx8rtss/__init__.py
qlx8rtss/model/__init__.py
qlx8rtss/model/ckpt_fold-01.pth
qlx8rtss/model/predict.py
qlx8rtss/model/sleepyco_net.py
qlx8rtss-0.1.0.dist-info/licenses/LICENSE
qlx8rtss-0.1.0.dist-info/METADATA
qlx8rtss-0.1.0.dist-info/WHEEL
qlx8rtss-0.1.0.dist-info/top_level.txt
qlx8rtss-0.1.0.dist-info/RECORD
