Metadata-Version: 2.4
Name: qlx8rtss
Version: 0.1.0
Summary: a python analyse sdk for QLan realtime sleep staging analysis
Author: scg
Author-email: shangweb001@gmail.com
License: MIT License
Keywords: eeg realtime sleep staging analysis
Platform: any
License-File: LICENSE
Requires-Dist: qlsdk2
Requires-Dist: scipy
Requires-Dist: numpy
Requires-Dist: torch
Requires-Dist: pandas
Requires-Dist: PySide6
Dynamic: author
Dynamic: author-email
Dynamic: keywords
Dynamic: license
Dynamic: license-file
Dynamic: platform
Dynamic: requires-dist
Dynamic: summary
